kode256/Inconsolata-Regular.ttf
kode256/__init__.py
kode256/__main__.py
kode256/format.py
kode256/image.py
kode256/svg.py
kode256/tool/ModifiedMixin.py
kode256/tool/__init__.py
kode256/tool/console.py
kode256/tool/gui.py
kode256-0.4b1.dist-info/LICENSE.txt
kode256-0.4b1.dist-info/METADATA
kode256-0.4b1.dist-info/WHEEL
kode256-0.4b1.dist-info/entry_points.txt
kode256-0.4b1.dist-info/top_level.txt
kode256-0.4b1.dist-info/RECORD
