Metadata-Version: 2.1
Name: kode256
Version: 0.4b1
Summary: Create code128 barcodes
Home-page: https://gitlab.com/bhowell/kode256
Author: Brendan Howell, Felix Knopf
Author-email: brendan-soc@howell-ersatz.com
License: LGPLv2+
Keywords: barcode
Platform: UNKNOWN
Classifier: Development Status :: 4 - Beta
Classifier: Environment :: Console
Classifier: License :: OSI Approved :: GNU Lesser General Public License v2 or later (LGPLv2+)
Classifier: Operating System :: OS Independent
Classifier: Programming Language :: Python :: 3
Classifier: Topic :: Utilities
Provides-Extra: pil
Requires-Dist: Pillow (>=2.7.0) ; extra == 'pil'
